AUTHORS.md
LICENSE
README.rst
setup.py
instaloader/__init__.py
instaloader/__main__.py
instaloader/exceptions.py
instaloader/instaloader.py
instaloader/instaloadercontext.py
instaloader/lateststamps.py
instaloader/nodeiterator.py
instaloader/py.typed
instaloader/structures.py
instaloader.egg-info/PKG-INFO
instaloader.egg-info/SOURCES.txt
instaloader.egg-info/dependency_links.txt
instaloader.egg-info/entry_points.txt
instaloader.egg-info/not-zip-safe
instaloader.egg-info/requires.txt
instaloader.egg-info/top_level.txt